setup.py
baoh_operations/Basicoperations.py
baoh_operations/Operations.py
baoh_operations/__init__.py
baoh_operations.egg-info/PKG-INFO
baoh_operations.egg-info/SOURCES.txt
baoh_operations.egg-info/dependency_links.txt
baoh_operations.egg-info/not-zip-safe
baoh_operations.egg-info/top_level.txt