Metadata-Version: 1.0
Name: baoh-operations
Version: 1.0.0
Summary: My pypi package for basic algebra
Home-page: UNKNOWN
Author: Bao Hoang
Author-email: baohoang.1988@gmail.com
License: UNKNOWN
Platform: UNKNOWN
